pyLICOS/__init__.py
pyLICOS/client.py
pyLICOS/communication.py
pyLICOS-0.2.4.dist-info/METADATA
pyLICOS-0.2.4.dist-info/WHEEL
pyLICOS-0.2.4.dist-info/top_level.txt
pyLICOS-0.2.4.dist-info/RECORD
