Metadata-Version: 2.1
Name: pyLICOS
Version: 0.2.4
Summary: Python interface for LICOS.
Author: Brian Yui Eto
Author-email: helppy.licos@linearsm.com.br
Classifier: Programming Language :: Python :: 3
Requires-Python: >=3.11
Requires-Dist: requests
